intercode/__init__.py
intercode/linear_decoder.py
intercode/model.py
intercode/utils.py
intercode-0.0.7.dist-info/LICENSE
intercode-0.0.7.dist-info/METADATA
intercode-0.0.7.dist-info/WHEEL
intercode-0.0.7.dist-info/top_level.txt
intercode-0.0.7.dist-info/RECORD
