Metadata-Version: 2.1
Name: intercode
Version: 0.0.7
Summary: Interpretable Autoencoder
Home-page: https://github.com/theislab/intercode
Author: Sergei Rybakov
Author-email: sergei.rybakov@helmholtz-muenchen.de
License: BSD-3-Clause
Platform: UNKNOWN
Classifier: Programming Language :: Python :: 3.6
Classifier: Programming Language :: Python :: 3.7
Classifier: Environment :: Console
Classifier: Framework :: Jupyter
Classifier: Intended Audience :: Developers
Classifier: Intended Audience :: Science/Research
Classifier: Natural Language :: English
Classifier: Operating System :: MacOS :: MacOS X
Classifier: Operating System :: Microsoft :: Windows
Classifier: Operating System :: POSIX :: Linux
Requires-Dist: anndata
Requires-Dist: torch
Requires-Dist: numpy
Requires-Dist: scikit-learn
